ccc/coef/__init__.py
ccc/coef/impl.py
ccc/numpy/__init__.py
ccc/pytorch/__init__.py
ccc/pytorch/core.py
ccc/scipy/__init__.py
ccc/scipy/stats.py
ccc/sklearn/__init__.py
ccc/sklearn/metrics.py
ccc/utils/__init__.py
ccc/utils/utility_functions.py
ccc_coef-0.2.2.dist-info/LICENSE
ccc_coef-0.2.2.dist-info/LICENSE_bundled
ccc_coef-0.2.2.dist-info/METADATA
ccc_coef-0.2.2.dist-info/WHEEL
ccc_coef-0.2.2.dist-info/top_level.txt
ccc_coef-0.2.2.dist-info/RECORD
