Metadata-Version: 2.1
Name: ccc-coef
Version: 0.2.2
Summary: The Clustermatch Correlation Coefficient (CCC) is a highly-efficient, next-generation not-only-linear correlation coefficient that can work on numerical and categorical data types.
Home-page: https://github.com/greenelab/ccc
Author: Milton Pividori
Author-email: miltondp@gmail.com
License: BSD-2-Clause Plus Patent
Classifier: Programming Language :: Python :: 3
Classifier: License :: OSI Approved :: BSD License
Classifier: Operating System :: OS Independent
Classifier: Development Status :: 5 - Production/Stable
Classifier: Environment :: Console
Requires-Python: >=3.9
License-File: LICENSE
License-File: LICENSE_bundled
Requires-Dist: numpy >=1.21.0
Requires-Dist: scipy
Requires-Dist: numba
